textpolicy/__init__.py
textpolicy/__main__.py
textpolicy/cli.py
textpolicy/validate.py
textpolicy/algorithms/__init__.py
textpolicy/algorithms/grpo.py
textpolicy/algorithms/gspo.py
textpolicy/buffer/__init__.py
textpolicy/buffer/buffer.py
textpolicy/buffer/episode.py
textpolicy/buffer/sampling.py
textpolicy/buffer/storage.py
textpolicy/environment/__init__.py
textpolicy/environment/base.py
textpolicy/environment/environment.py
textpolicy/environment/factory.py
textpolicy/environment/gym.py
textpolicy/environment/task_suites.py
textpolicy/environment/text_generation.py
textpolicy/environment/vectorized.py
textpolicy/generation/__init__.py
textpolicy/generation/lora.py
textpolicy/generation/mlx_generation.py
textpolicy/generation/reload.py
textpolicy/rewards/__init__.py
textpolicy/rewards/adapters.py
textpolicy/rewards/basic.py
textpolicy/rewards/integrated_system.py
textpolicy/rewards/mlx_batch_processor.py
textpolicy/rewards/registry.py
textpolicy/rewards/rollout_rewards.py
textpolicy/rewards/verifiers.py
textpolicy/rollout/__init__.py
textpolicy/rollout/aggregator.py
textpolicy/rollout/base.py
textpolicy/rollout/rollout.py
textpolicy/rollout/runner.py
textpolicy/rollout/strategy.py
textpolicy/rollout/worker.py
textpolicy/training/__init__.py
textpolicy/training/metrics.py
textpolicy/training/rollout_manager.py
textpolicy/training/trainer.py
textpolicy/utils/__init__.py
textpolicy/utils/benchmarking.py
textpolicy/utils/data.py
textpolicy/utils/debug.py
textpolicy/utils/environment.py
textpolicy/utils/memory.py
textpolicy/utils/performance.py
textpolicy/utils/timing.py
textpolicy/utils/logging/__init__.py
textpolicy/utils/logging/base.py
textpolicy/utils/logging/console.py
textpolicy/utils/logging/factory.py
textpolicy/utils/logging/multi.py
textpolicy/utils/logging/tensorboard.py
textpolicy/utils/logging/wandb.py
textpolicy/validation/__init__.py
textpolicy/validation/logprob_validation.py
textpolicy-0.1.0.dist-info/licenses/LICENSE
textpolicy-0.1.0.dist-info/METADATA
textpolicy-0.1.0.dist-info/WHEEL
textpolicy-0.1.0.dist-info/entry_points.txt
textpolicy-0.1.0.dist-info/top_level.txt
textpolicy-0.1.0.dist-info/RECORD
