Metadata-Version: 2.4
Name: textpolicy
Version: 0.1.0
Summary: MLX-optimized reward and verification system for text generation RL
Requires-Python: >=3.12
License-File: LICENSE
Requires-Dist: numpy>=2.3.2
Requires-Dist: mlx>=0.21.0
Requires-Dist: mlx-lm>=0.21.0
Requires-Dist: gymnasium>=0.29.0
Requires-Dist: psutil>=7.0.0
Requires-Dist: wandb>=0.21.1
Requires-Dist: aiohttp>=3.12.15
Requires-Dist: pytest>=8.4.1
Provides-Extra: external
Requires-Dist: aiohttp>=3.8.0; extra == "external"
Requires-Dist: pydantic>=2.0.0; extra == "external"
Provides-Extra: dev
Requires-Dist: pytest>=7.0.0; extra == "dev"
Requires-Dist: black>=22.0.0; extra == "dev"
Requires-Dist: ruff>=0.1.0; extra == "dev"
Dynamic: license-file
